{
  "meta": {
    "created_at": "2026-03-10T12:35:00.929092Z",
    "last_updated": "2026-03-11T09:58:16.172966Z",
    "total_accounts": 20,
    "description": "Molty Royale Account Database",
    "db_path": "C:\\Users\\viikemx\\Downloads\\molty3-main (3)\\molty3-main\\accounts_db.json"
  },
  "accounts": [
    {
      "accountId": "4e4003e9-e909-47fc-89c8-c5781484491b",
      "name": "shaheed",
      "apiKey": "mr_live_R7hk1R5fR9n2qNaI91DfqUt015lars5W",
      "verificationCode": "",
      "publicId": "109742543848925",
      "walletAddress": "0xca7ea55dbeff5e1da722774f5b0d538fc4a0c831",
      "walletSynced": true,
      "balance": 0,
      "crossBalanceWei": "0",
      "totalGames": 0,
      "totalWins": 0,
      "currentGames": [
        {
          "gameId": "71f4273b-65c0-4d3a-acea-0da6936a8096",
          "agentId": "61230f59-6566-467d-99ca-6af57a6ac0b9",
          "agentName": "shaheed",
          "isAlive": 1,
          "gameStatus": "running",
          "entryType": "free"
        }
      ],
      "createdAt": "2026-03-10T12:41:26.696Z",
      "lastUpdated": "2026-03-11T09:54:47.662865Z",
      "notes": "bulk_create"
    },
    {
      "accountId": "f5fc4c52-9e42-479f-a822-1d3ba33c6f0b",
      "name": "martyr",
      "apiKey": "mr_live_TXs_O0BfgDCTXzn2x85m9GdhpZhgY2eQ",
      "verificationCode": "",
      "publicId": "144031140908200",
      "walletAddress": "0x129ebf8282abcdebea30e419f7448fdd2ad4f9ca",
      "walletSynced": true,
      "balance": 0,
      "crossBalanceWei": "0",
      "totalGames": 0,
      "totalWins": 0,
      "currentGames": [
        {
          "gameId": "84b8db9a-ac78-4683-8d42-fe27a66f2251",
          "agentId": "3a95d698-934a-450e-af33-7bc1d7efb8ff",
          "agentName": "martyr",
          "isAlive": 1,
          "gameStatus": "running",
          "entryType": "free"
        }
      ],
      "createdAt": "2026-03-10T12:41:29.768Z",
      "lastUpdated": "2026-03-11T09:54:48.188212Z",
      "notes": "bulk_create"
    },
    {
      "accountId": "209eff2a-9aa7-455b-bb8a-75744ca95563",
      "name": "owo",
      "apiKey": "mr_live_RKl6S9HC01REKSd1Cd_5a7Sstv8dGg0j",
      "verificationCode": "",
      "publicId": "239913463039479",
      "walletAddress": "0x055573471195e81fc49e40619c9e49d0d4a3b835",
      "walletSynced": true,
      "balance": 0,
      "crossBalanceWei": "0",
      "totalGames": 0,
      "totalWins": 0,
      "currentGames": [
        {
          "gameId": "71f4273b-65c0-4d3a-acea-0da6936a8096",
          "agentId": "3269538b-a041-48c5-9597-5ebae09548e0",
          "agentName": "owo",
          "isAlive": 0,
          "gameStatus": "running",
          "entryType": "free"
        }
      ],
      "createdAt": "2026-03-10T12:41:33.107Z",
      "lastUpdated": "2026-03-11T09:54:48.722470Z",
      "notes": "bulk_create"
    },
    {
      "accountId": "fa9eb3cd-3089-45d9-a4b7-8b40bcb6880f",
      "name": "owi",
      "apiKey": "mr_live_m2jU8TAc7aQawZFPQNGQ2EJBWHuC3Uxn",
      "verificationCode": "",
      "publicId": "134538086231639",
      "walletAddress": "0x32f249389653f8043f94435a44bc27f5c40677a0",
      "walletSynced": true,
      "balance": 18,
      "crossBalanceWei": "0",
      "totalGames": 0,
      "totalWins": 0,
      "currentGames": [
        {
          "gameId": "84b8db9a-ac78-4683-8d42-fe27a66f2251",
          "agentId": "6f9c04e5-22a9-4d32-8fbb-5cfdce23fbc4",
          "agentName": "owi",
          "isAlive": 0,
          "gameStatus": "running",
          "entryType": "free"
        }
      ],
      "createdAt": "2026-03-10T12:41:36.192Z",
      "lastUpdated": "2026-03-11T09:58:16.172800Z",
      "notes": "bulk_create",
      "scWallet": "0xcf129ee0581bb2cbdf33cf2188f9c07c404a8095",
      "scOwnerEoa": "0x32f249389653f8043f94435a44bc27f5c40677a0",
      "whitelistStatus": "approved",
      "onchainTxHash": "06d215bf5769a806ae5895c0d0a2561f6e9d65a3e9169b80e2eca44ea369353e"
    },
    {
      "accountId": "96de7e0a-7d85-4874-b801-2c19b8c7d3c4",
      "name": "gib",
      "apiKey": "mr_live_9AJ-_u0miGyQFTub5nCgCPw2n6XM1JvU",
      "verificationCode": "",
      "publicId": "50580070681789",
      "walletAddress": "0x38606681e5674d52acef946cb294fc6dbb39fde5",
      "walletSynced": true,
      "balance": 0,
      "crossBalanceWei": "0",
      "totalGames": 0,
      "totalWins": 0,
      "currentGames": [
        {
          "gameId": "71f4273b-65c0-4d3a-acea-0da6936a8096",
          "agentId": "0a0fddc5-3483-4aa8-933e-314e46bf8cf0",
          "agentName": "gib",
          "isAlive": 1,
          "gameStatus": "running",
          "entryType": "free"
        }
      ],
      "createdAt": "2026-03-10T12:41:39.267Z",
      "lastUpdated": "2026-03-11T09:54:49.754513Z",
      "notes": "bulk_create"
    },
    {
      "accountId": "370c69b7-f27c-4eed-8f8b-eaa1506ac7bb",
      "name": "robinhood",
      "apiKey": "mr_live_l7ZyulIw4RyJW0mdQ4V6F7svtQjtauai",
      "verificationCode": "",
      "publicId": "267318022047931",
      "walletAddress": "0xea304a712c560f843de68496485c6db3bee6e670",
      "walletSynced": true,
      "balance": 5,
      "crossBalanceWei": "0",
      "totalGames": 0,
      "totalWins": 0,
      "currentGames": [
        {
          "gameId": "00de06bc-8893-42f9-9100-4595cd57af9f",
          "agentId": "d23baae6-f38a-47fa-a13d-cca12fc91139",
          "agentName": "robinhood",
          "isAlive": 0,
          "gameStatus": "running",
          "entryType": "free"
        }
      ],
      "createdAt": "2026-03-10T13:29:44.617Z",
      "lastUpdated": "2026-03-11T09:54:50.263363Z",
      "notes": "bulk_create"
    },
    {
      "accountId": "b4728046-b051-4480-8f53-2122759d4e71",
      "name": "elPEMENANG",
      "apiKey": "mr_live_i8ypG8pBjrif7ZNBod099ugcICeQIS0-",
      "verificationCode": "",
      "publicId": "72147335672172",
      "walletAddress": "0x7cd851054e11a406466cb2b04dd9440a7e82e040",
      "walletSynced": true,
      "balance": 0,
      "crossBalanceWei": "0",
      "totalGames": 0,
      "totalWins": 0,
      "currentGames": [
        {
          "gameId": "02232759-ddab-45e1-b018-d0e26fe30c5a",
          "agentId": "1c84c2dd-744c-4af7-b029-8713df51cb30",
          "agentName": "elPEMENANG",
          "isAlive": 0,
          "gameStatus": "running",
          "entryType": "free"
        }
      ],
      "createdAt": "2026-03-10T13:29:47.821Z",
      "lastUpdated": "2026-03-11T09:54:51.027407Z",
      "notes": "bulk_create"
    },
    {
      "accountId": "32a7b018-255b-4b65-b2cf-a3d024373f24",
      "name": "a7jtloker",
      "apiKey": "mr_live_ocqgtnqGyAWwJE9xcVzdWVZvIcu0IACH",
      "verificationCode": "",
      "publicId": "238251157775103",
      "walletAddress": "0x5c81708c9c1cfab4280e938259ce4f89bdc2e01b",
      "walletSynced": true,
      "balance": 0,
      "crossBalanceWei": "0",
      "totalGames": 0,
      "totalWins": 0,
      "currentGames": [
        {
          "gameId": "cb0a22e8-dc52-469d-b04b-b6cdd8d4fb7a",
          "agentId": "e8d39929-da8d-44bd-b3d5-08f88de19894",
          "agentName": "a7jtloker",
          "isAlive": 0,
          "gameStatus": "running",
          "entryType": "free"
        }
      ],
      "createdAt": "2026-03-10T13:29:50.895Z",
      "lastUpdated": "2026-03-11T09:54:51.560538Z",
      "notes": "bulk_create"
    },
    {
      "accountId": "702276c6-6b7e-4e56-a602-99e7a03a823f",
      "name": "epstenpedo",
      "apiKey": "mr_live_zWFJlJNqy62fUYKwEtrT4Sv03Q-zJ_tD",
      "verificationCode": "",
      "publicId": "54787456063466",
      "walletAddress": "0x0c5e7107b6cfa677f0aabdc5d616c5fef27ca7cd",
      "walletSynced": true,
      "balance": 0,
      "crossBalanceWei": "0",
      "totalGames": 0,
      "totalWins": 0,
      "currentGames": [
        {
          "gameId": "2ccf4bc0-67dd-4662-86b6-818082e1ed7d",
          "agentId": "86e922ee-ac76-4632-8468-e9543b499f65",
          "agentName": "epstenpedo",
          "isAlive": 0,
          "gameStatus": "running",
          "entryType": "free"
        }
      ],
      "createdAt": "2026-03-10T13:29:53.946Z",
      "lastUpdated": "2026-03-11T09:54:52.074234Z",
      "notes": "bulk_create"
    },
    {
      "accountId": "79b5a287-6fdd-4c68-bf31-a3836ea33858",
      "name": "trumpedo",
      "apiKey": "mr_live_rO1DMc-X0vUiXMmLJ3Io88YYdyX4cecS",
      "verificationCode": "",
      "publicId": "207456116573012",
      "walletAddress": "0x02b665d47578d07513b4dafcc8ff50dbdace9e00",
      "walletSynced": true,
      "balance": 0,
      "crossBalanceWei": "0",
      "totalGames": 0,
      "totalWins": 0,
      "currentGames": [],
      "createdAt": "2026-03-10T13:29:57.004Z",
      "lastUpdated": "2026-03-11T09:54:52.588168Z",
      "notes": "bulk_create"
    },
    {
      "accountId": "6db1b6c9-0272-4491-8480-7e0762174ad9",
      "name": "robbi",
      "apiKey": "mr_live_b2VDNuBeWoBukR7kf8ZzdWnqz4UdJbOp",
      "verificationCode": "",
      "publicId": "167128607195493",
      "walletAddress": "0xb0653166fdef02fc7baca0145a16a1392d5bfd54",
      "walletSynced": true,
      "balance": 0,
      "crossBalanceWei": "0",
      "totalGames": 0,
      "totalWins": 0,
      "currentGames": [
        {
          "gameId": "54541a9a-c69d-4343-8c89-dcbfb7908bc1",
          "agentId": "44df3e92-ea3e-476c-a689-50664fea04cc",
          "agentName": "robbi",
          "isAlive": 1,
          "gameStatus": "running",
          "entryType": "free"
        }
      ],
      "createdAt": "2026-03-10T15:47:58.706Z",
      "lastUpdated": "2026-03-11T09:54:53.108772Z",
      "notes": "bulk_create"
    },
    {
      "accountId": "2dc9eb77-f3f3-4428-9165-a933e2f2dabf",
      "name": "marcielle28",
      "apiKey": "mr_live_4ShRQOn_kbYhhqERcmZRw6BZl6gyuRD-",
      "verificationCode": "",
      "publicId": "182468888442874",
      "walletAddress": "0xbedb2b1fdcc75a08f82217da2e914e0cc3570d0c",
      "walletSynced": true,
      "balance": 0,
      "crossBalanceWei": "0",
      "totalGames": 0,
      "totalWins": 0,
      "currentGames": [
        {
          "gameId": "525512e4-a9fa-41bf-bc79-953da0cc7d42",
          "agentId": "21ca68e6-6dc6-4485-859b-123cd5604f21",
          "agentName": "marcielle28",
          "isAlive": 0,
          "gameStatus": "running",
          "entryType": "free"
        }
      ],
      "createdAt": "2026-03-10T15:48:01.760Z",
      "lastUpdated": "2026-03-11T09:54:53.646056Z",
      "notes": "bulk_create"
    },
    {
      "accountId": "03fdb283-7279-48c2-b501-40a78106a0ee",
      "name": "fourb",
      "apiKey": "mr_live_PpVJfK0wfjoSXwimQNspIMHVEeiURaPG",
      "verificationCode": "",
      "publicId": "183732993331228",
      "walletAddress": "0xfbf0d20d0a31c15e2eea0d68e2338eadab508e93",
      "walletSynced": true,
      "balance": 0,
      "crossBalanceWei": "0",
      "totalGames": 0,
      "totalWins": 0,
      "currentGames": [
        {
          "gameId": "da037cc4-3324-441c-8bbd-3b4dc88d422e",
          "agentId": "d8dc4573-f4d0-4f58-aaa5-17fa9cf815d4",
          "agentName": "fourb",
          "isAlive": 1,
          "gameStatus": "running",
          "entryType": "free"
        }
      ],
      "createdAt": "2026-03-10T15:48:04.817Z",
      "lastUpdated": "2026-03-11T09:54:54.162363Z",
      "notes": "bulk_create"
    },
    {
      "accountId": "b4cac6ad-f36f-44e1-843c-19997eab17ba",
      "name": "ratna",
      "apiKey": "mr_live_vVnGLi15yVodGOhPvuKmGYlkhQHXMylC",
      "verificationCode": "",
      "publicId": "28535254764390",
      "walletAddress": "0xfa9bd18e091edc5db622897a66329ae66f3fe3de",
      "walletSynced": true,
      "balance": 0,
      "crossBalanceWei": "0",
      "totalGames": 0,
      "totalWins": 0,
      "currentGames": [
        {
          "gameId": "54541a9a-c69d-4343-8c89-dcbfb7908bc1",
          "agentId": "e903c75b-f691-4b10-a495-4501c438f982",
          "agentName": "ratna",
          "isAlive": 1,
          "gameStatus": "running",
          "entryType": "free"
        }
      ],
      "createdAt": "2026-03-10T15:48:07.911Z",
      "lastUpdated": "2026-03-11T09:54:54.674141Z",
      "notes": "bulk_create"
    },
    {
      "accountId": "01b04898-60ce-4c74-b1c8-a03213e1f395",
      "name": "arang",
      "apiKey": "mr_live_Pk-qlM4_77xCWv89BX314CkWJnZ7EMRb",
      "verificationCode": "",
      "publicId": "208376519871413",
      "walletAddress": "0x32d2b0c5cd4b70d9013593d76eb1cf1143cf5fe0",
      "walletSynced": true,
      "balance": 0,
      "crossBalanceWei": "0",
      "totalGames": 0,
      "totalWins": 0,
      "currentGames": [
        {
          "gameId": "54541a9a-c69d-4343-8c89-dcbfb7908bc1",
          "agentId": "6992a39c-45b3-4bbc-a1c6-867859158135",
          "agentName": "arang",
          "isAlive": 0,
          "gameStatus": "running",
          "entryType": "free"
        }
      ],
      "createdAt": "2026-03-10T15:48:11.328Z",
      "lastUpdated": "2026-03-11T09:54:55.189271Z",
      "notes": "bulk_create"
    },
    {
      "accountId": "2ad70f03-3092-4445-b48c-16c2ccc6b05a",
      "name": "ardan",
      "apiKey": "mr_live_iln7Ir_bIgQzKGEe2ikkZ029tR9LiRlx",
      "verificationCode": "",
      "publicId": "175315336608464",
      "walletAddress": "0x59392331c635cabcfb3f5cbcce99c4319c9e6b7e",
      "walletSynced": true,
      "balance": 0,
      "crossBalanceWei": "0",
      "totalGames": 0,
      "totalWins": 0,
      "currentGames": [
        {
          "gameId": "a9c0f275-f6bf-4ac4-bf4c-26375ad78c00",
          "agentId": "d3737806-f4d9-4801-8ea6-0fc7b0e4a12d",
          "agentName": "ardan",
          "isAlive": 0,
          "gameStatus": "running",
          "entryType": "free"
        }
      ],
      "createdAt": "2026-03-10T15:49:30.155Z",
      "lastUpdated": "2026-03-11T09:54:55.941019Z",
      "notes": "bulk_create"
    },
    {
      "accountId": "784e6a98-d34f-4357-bd0f-86d505b94958",
      "name": "fikri",
      "apiKey": "mr_live_ZvtHoGuu9uhGScNJXiazrrCBWdq6d8ro",
      "verificationCode": "",
      "publicId": "212828919103434",
      "walletAddress": "0x635a10d287a2b44895199fa740607d8860a50c2a",
      "walletSynced": true,
      "balance": 0,
      "crossBalanceWei": "0",
      "totalGames": 0,
      "totalWins": 0,
      "currentGames": [
        {
          "gameId": "db13c9ce-d91c-435d-b102-43e5caeba1de",
          "agentId": "040e59fc-e207-48bf-be99-075639987747",
          "agentName": "fikri",
          "isAlive": 0,
          "gameStatus": "running",
          "entryType": "free"
        }
      ],
      "createdAt": "2026-03-10T15:49:33.230Z",
      "lastUpdated": "2026-03-11T09:54:56.453244Z",
      "notes": "bulk_create"
    },
    {
      "accountId": "5b36dfb9-fdb0-424c-83ac-85bceb6898cb",
      "name": "kim",
      "apiKey": "mr_live_P4MMolsvaTZ3IQoTZLVrBYpPC8qOZYEz",
      "verificationCode": "",
      "publicId": "196346420024143",
      "walletAddress": "0x31be539123c669b5bc496543dbbae1579f88d18c",
      "walletSynced": true,
      "balance": 0,
      "crossBalanceWei": "0",
      "totalGames": 0,
      "totalWins": 0,
      "currentGames": [
        {
          "gameId": "a9c0f275-f6bf-4ac4-bf4c-26375ad78c00",
          "agentId": "5ec4330c-03b1-44ea-935f-af9f9ca07e07",
          "agentName": "kim",
          "isAlive": 0,
          "gameStatus": "running",
          "entryType": "free"
        }
      ],
      "createdAt": "2026-03-10T15:49:36.620Z",
      "lastUpdated": "2026-03-11T09:54:57.007050Z",
      "notes": "bulk_create"
    },
    {
      "accountId": "5538bf69-237d-429b-b4cc-73c1bab87c99",
      "name": "harry",
      "apiKey": "mr_live_Wtjky9eGsPHEQwtFoIeJpNUdyIIlzmxU",
      "verificationCode": "",
      "publicId": "63786403237601",
      "walletAddress": "0x3a4fe4fd896fa7e709d8239fb9f55b77d1d712f0",
      "walletSynced": true,
      "balance": 0,
      "crossBalanceWei": "0",
      "totalGames": 0,
      "totalWins": 0,
      "currentGames": [
        {
          "gameId": "a9c0f275-f6bf-4ac4-bf4c-26375ad78c00",
          "agentId": "1b231cc4-4106-4e59-a0a1-b6980504946d",
          "agentName": "harry",
          "isAlive": 0,
          "gameStatus": "running",
          "entryType": "free"
        }
      ],
      "createdAt": "2026-03-10T15:49:39.859Z",
      "lastUpdated": "2026-03-11T09:54:57.545294Z",
      "notes": "bulk_create"
    },
    {
      "accountId": "bfebcaec-25a3-47e5-903e-90779a99269b",
      "name": "cuna",
      "apiKey": "mr_live_4titQVuuqmqFOC_pJS7p-RMCWyY2cR_D",
      "verificationCode": "",
      "publicId": "197309473267144",
      "walletAddress": "0x94a42e6b67d5af0c7bc98696617fc66e7440d98e",
      "walletSynced": true,
      "balance": 0,
      "crossBalanceWei": "0",
      "totalGames": 0,
      "totalWins": 0,
      "currentGames": [
        {
          "gameId": "db13c9ce-d91c-435d-b102-43e5caeba1de",
          "agentId": "f34f66f1-b420-41ae-a564-13037b366401",
          "agentName": "cuna",
          "isAlive": 1,
          "gameStatus": "running",
          "entryType": "free"
        }
      ],
      "createdAt": "2026-03-10T15:49:43.513Z",
      "lastUpdated": "2026-03-11T09:54:58.239459Z",
      "notes": "bulk_create"
    }
  ]
}